fatld/__init__.py
fatld/design.py
fatld/main.py
fatld/relation.py
fatld-0.1.11.dist-info/METADATA
fatld-0.1.11.dist-info/WHEEL
fatld-0.1.11.dist-info/RECORD
