Metadata-Version: 2.1
Name: fatld
Version: 0.1.11
Summary: Generate and characterize designs with four-and-two-level (FATL) factors
Home-page: https://abohyndoe.github.io/fatld/
License: MIT
Keywords: design,doe
Author: Alexandre Bohyn
Author-email: alexandre.bohyn@kuleuven.be
Requires-Python: >=3.8,<4.0
Classifier: Development Status :: 3 - Alpha
Classifier: License :: OSI Approved :: MIT License
Classifier: Programming Language :: Python :: 3
Classifier: Programming Language :: Python :: 3.8
Classifier: Programming Language :: Python :: 3.9
Classifier: Programming Language :: Python :: 3.10
Classifier: Programming Language :: Python :: 3.11
Classifier: Programming Language :: Python :: 3.8
Requires-Dist: matplotlib (>=3.6.3,<4.0.0)
Requires-Dist: numpy (>=1.24.2,<2.0.0)
Requires-Dist: oapackage (>=2.7.6,<3.0.0)
Requires-Dist: pandas (>=1.5.3,<2.0.0)
Project-URL: Repository, https://github.com/ABohynDOE/fatld
